strulab/__init__.py
strulab-0.0.0.dist-info/METADATA
strulab-0.0.0.dist-info/WHEEL
strulab-0.0.0.dist-info/top_level.txt
strulab-0.0.0.dist-info/RECORD
