Metadata-Version: 2.4
Name: strulab
Version: 0.0.0
Summary: Structure Laboratory
Author-email: DalNur <liyang@alu.hit.edu.cn>
Project-URL: Homepage, https://github.com/DalNur/strulab
Classifier: Programming Language :: Python :: 3
Classifier: License :: OSI Approved :: MIT License
Requires-Python: >=3.8
